[
  {
    "id": "9bd93a8a-1fcb-405a-b2e3-4a283915bbca",
    "key": "responsive-web-design-certification",
    "providerName": "freeCodeCamp",
    "providerCertificationId": "561add10cb82ac38a17513bc",
    "title": "Responsive Web Design Certification",
    "certification": "responsive-web-design",
    "completionHours": 300,
    "courses": [
      "2022/responsive-web-design"
    ],
    "state": "active",
    "category": "Web Development",
    "trackType": "DEV",
    "certType": "certification"
  },
  {
    "id": "aae0ba52-18fe-4c8e-ac4f-fd55715c8b5d",
    "key": "javascript-algorithms-and-data-structures-certification",
    "providerCertificationId": "561abd10cb81ac38a17513bc",
    "providerName": "freeCodeCamp",
    "title": "JavaScript Algorithms and Data Structures Certification",
    "certification": "javascript-algorithms-and-data-structures",
    "completionHours": 300,
    "courses": [
      "javascript-algorithms-and-data-structures"
    ],
    "state": "active",
    "category": "Web Development",
    "trackType": "DEV",
    "certType": "certification"
  },
  {
    "id": "6909044d-508b-4c6e-9b90-999bea2b82b0",
    "key": "front-end-development-libraries-certification",
    "providerCertificationId": "561acd10cb82ac38a17513bc",
    "providerName": "freeCodeCamp",
    "title": "Front End Development Libraries Certification",
    "certification": "front-end-development-libraries-certification",
    "completionHours": 300,
    "courses": [
      "front-end-development-libraries"
    ],
    "state": "active",
    "category": "Web Development",
    "trackType": "DEV",
    "certType": "certification"
  },
  {
    "id": "55597a63-e23e-4bc0-9a81-b4f5655a96eb",
    "key": "data-visualization-certification",
    "providerCertificationId": "5a553ca864b52e1d8bceea14",
    "providerName": "freeCodeCamp",
    "title": "Data Visualization",
    "certification": "data-visualization",
    "completionHours": 300,
    "courses": [
      "data-visualization"
    ],
    "state": "active",
    "category": "Data Science",
    "trackType": "DATASCIENCE",
    "certType": "certification"
  },
  {
    "id": "9796fe32-d2f9-4b1b-92ee-c6003e4400ac",
    "key": "scientific-computing-with-python-certification",
    "providerCertificationId": "5e44431b903586ffb414c951",
    "providerName": "freeCodeCamp",
    "title": "Scientific Computing with Python",
    "certification": "scientific-computing-with-python",
    "completionHours": 300,
    "courses": [
      "scientific-computing-with-python"
    ],
    "state": "active",
    "category": "Data Science",
    "trackType": "DATASCIENCE",
    "certType": "certification"
  },
  {
    "id": "269f7d9d-fb10-402b-a942-600f025b0c0f",
    "key": "data-analysis-with-python-certification",
    "providerCertificationId": "5e46fc95ac417301a38fb934",
    "providerName": "freeCodeCamp",
    "title": "Data Analysis with Python",
    "certification": "data-analysis-with-python",
    "completionHours": 300,
    "courses": [
      "data-analysis-with-python"
    ],
    "state": "active",
    "category": "Data Science",
    "trackType": "DATASCIENCE",
    "certType": "certification"
  }
]